Metadata-Version: 1.0
Name: uconfload
Version: 0.1.3
Summary: Universal config loader for standalone and containerized apps.
Home-page: https://github.com/edward2a/uconfload-python
Author: Eduardo A. Paris Penas
Author-email: edward2a@gmail.com, epp@realread.me
License: Apache License 2.0
Platform: UNKNOWN
